flock/__init__.py
flock/cli.py
flock/examples.py
flock/registry.py
flock/agent/__init__.py
flock/agent/builder_helpers.py
flock/agent/builder_validator.py
flock/agent/component_lifecycle.py
flock/agent/context_resolver.py
flock/agent/mcp_integration.py
flock/agent/mcp_server_config.py
flock/agent/output_processor.py
flock/api/__init__.py
flock/api/base_service.py
flock/api/collector.py
flock/api/graph_builder.py
flock/api/idempotency.py
flock/api/launcher.py
flock/api/models.py
flock/api/service.py
flock/api/themes.py
flock/api/webhooks.py
flock/api/websocket.py
flock/api/static_files/index.html
flock/api/static_files/assets/index-DFRnI_mt.js
flock/api/static_files/assets/index-fPLNdmp1.css
flock/components/__init__.py
flock/components/agent/__init__.py
flock/components/agent/base.py
flock/components/agent/output_utility.py
flock/components/orchestrator/__init__.py
flock/components/orchestrator/activation.py
flock/components/orchestrator/base.py
flock/components/orchestrator/circuit_breaker.py
flock/components/orchestrator/collection.py
flock/components/orchestrator/deduplication.py
flock/components/orchestrator/webhook.py
flock/components/orchestrator/scheduling/__init__.py
flock/components/orchestrator/scheduling/timer.py
flock/components/server/__init__.py
flock/components/server/base.py
flock/components/server/agents/__init__.py
flock/components/server/agents/agents_component.py
flock/components/server/artifacts/__init__.py
flock/components/server/artifacts/artifacts_component.py
flock/components/server/artifacts/models.py
flock/components/server/auth/__init__.py
flock/components/server/auth/auth_component.py
flock/components/server/control/__init__.py
flock/components/server/control/control_routes_component.py
flock/components/server/control/helpers.py
flock/components/server/cors/__init__.py
flock/components/server/cors/cors_component.py
flock/components/server/health/__init__.py
flock/components/server/health/health_component.py
flock_core-0.5.318.dist-info/METADATA
flock_core-0.5.318.dist-info/WHEEL
flock_core-0.5.318.dist-info/entry_points.txt
flock_core-0.5.318.dist-info/licenses/LICENSE
flock_core-0.5.318.dist-info/RECORD
