Metadata-Version: 2.4
Name: flock-core
Version: 0.5.318
Summary: Flock: A declrative framework for building and orchestrating AI agents.
Author-email: Andre Ratzenberger <andre.ratzenberger@whiteduck.de>
License: MIT
License-File: LICENSE
Requires-Python: >=3.12
Requires-Dist: aiosqlite==0.21.0
Requires-Dist: croniter==6.0.0
Requires-Dist: devtools==0.12.2
Requires-Dist: dspy==3.0.3
Requires-Dist: duckdb==1.4.1
Requires-Dist: fastapi==0.121.0
Requires-Dist: hanging-threads==2.0.7
Requires-Dist: httpx==0.28.1
Requires-Dist: litellm==1.78.0
Requires-Dist: loguru==0.7.3
Requires-Dist: mcp==1.20.0
Requires-Dist: opentelemetry-api==1.34.1
Requires-Dist: opentelemetry-exporter-jaeger-proto-grpc==1.21.0
Requires-Dist: opentelemetry-exporter-jaeger==1.21.0
Requires-Dist: opentelemetry-exporter-otlp==1.34.1
Requires-Dist: opentelemetry-instrumentation-logging==0.55b1
Requires-Dist: opentelemetry-sdk==1.34.1
Requires-Dist: poethepoet==0.37.0
Requires-Dist: pydantic[email]==2.12.4
Requires-Dist: python-dotenv==1.2.1
Requires-Dist: rich==14.2.0
Requires-Dist: starlette==0.49.3
Requires-Dist: toml==0.10.2
Requires-Dist: typer==0.20.0
Requires-Dist: uvicorn==0.38.0
Requires-Dist: websockets==15.0.1
Provides-Extra: semantic
Requires-Dist: sentence-transformers==5.1.2; extra == 'semantic'
Provides-Extra: transformers
Requires-Dist: accelerate>=1.12.0; extra == 'transformers'
Requires-Dist: bitsandbytes>=0.48.2; extra == 'transformers'
Requires-Dist: transformers==4.55.0; extra == 'transformers'
